csaccess/__init__.py
csaccess/__main__.py
csaccess/constants.py
csaccess/rp.py
csaccess/utils.py
csaccess-0.1.0.dist-info/licenses/LICENSE
csaccess-0.1.0.dist-info/METADATA
csaccess-0.1.0.dist-info/WHEEL
csaccess-0.1.0.dist-info/entry_points.txt
csaccess-0.1.0.dist-info/top_level.txt
csaccess-0.1.0.dist-info/RECORD
