Metadata-Version: 2.4
Name: csaccess
Version: 0.1.0
Summary: A Python library for authenticating and accessing CONTACT resources in AWS.
Author-email: Alexander Vetski <alexander.vetski@contact-software.com>, Elias Haag <elias.haag@contact-software.com>
License:                                 Apache License
Project-URL: Homepage, https://contact-software.com
Classifier: Environment :: Console
Classifier: Development Status :: 5 - Production/Stable
Classifier: Intended Audience :: Developers
Classifier: Operating System :: OS Independent
Classifier: Programming Language :: Python :: 3
Classifier: Programming Language :: Python :: 3.9
Classifier: Programming Language :: Python :: 3.10
Classifier: Programming Language :: Python :: 3.11
Classifier: Programming Language :: Python :: 3.12
Classifier: Programming Language :: Python :: 3.13
Classifier: Topic :: Software Development
Classifier: License :: OSI Approved :: Apache Software License
Requires-Python: >=3.9
License-File: LICENSE
Requires-Dist: boto3~=1.38
Requires-Dist: oic~=1.7
Dynamic: license-file
